hvpdb_migrate/__init__.py
hvpdb_migrate-0.1.0.dist-info/METADATA
hvpdb_migrate-0.1.0.dist-info/WHEEL
hvpdb_migrate-0.1.0.dist-info/entry_points.txt
hvpdb_migrate-0.1.0.dist-info/top_level.txt
hvpdb_migrate-0.1.0.dist-info/RECORD
