Metadata-Version: 2.4
Name: hvpdb-migrate
Version: 0.1.0
Summary: Schema Migration Plugin for HVPDB
Requires-Dist: hvpdb
Dynamic: requires-dist
Dynamic: summary
